saml2_pro_auth/__init__.py
saml2_pro_auth/admin.py
saml2_pro_auth/apps.py
saml2_pro_auth/auth.py
saml2_pro_auth/constants.py
saml2_pro_auth/json_field.py
saml2_pro_auth/models.py
saml2_pro_auth/settings.py
saml2_pro_auth/urls.py
saml2_pro_auth/utils.py
saml2_pro_auth/views.py
saml2_pro_auth/migrations/0001_initial.py
saml2_pro_auth/migrations/__init__.py
django_saml2_pro_auth-1.0.1.dist-info/LICENSE
django_saml2_pro_auth-1.0.1.dist-info/METADATA
django_saml2_pro_auth-1.0.1.dist-info/WHEEL
django_saml2_pro_auth-1.0.1.dist-info/top_level.txt
django_saml2_pro_auth-1.0.1.dist-info/RECORD
