Metadata-Version: 2.1
Name: django-saml2-pro-auth
Version: 1.0.1
Summary: SAML2 authentication backend for Django wrapping OneLogins python-saml package https://github.com/onelogin/python3-saml
Home-page: https://github.com/zibasec/django-saml2-pro-auth
Author: Julie Davila
Author-email: julied@zibasec.io
License: MIT License
Keywords: sso,single-signon,authentication,saml,saml2,django,development,okta,onelogin
Platform: UNKNOWN
Classifier: Development Status :: 4 - Beta
Classifier: Intended Audience :: Developers
Classifier: Framework :: Django
Classifier: Framework :: Django :: 2.2
Classifier: Framework :: Django :: 3.0
Classifier: Framework :: Django :: 3.1
Classifier: Topic :: Security
Classifier: Topic :: System :: Systems Administration :: Authentication/Directory
Classifier: License :: OSI Approved :: MIT License
Classifier: Programming Language :: Python
Classifier: Programming Language :: Python :: 3
Classifier: Programming Language :: Python :: 3.5
Classifier: Programming Language :: Python :: 3.6
Classifier: Programming Language :: Python :: 3.7
Classifier: Programming Language :: Python :: 3.8
Classifier: Programming Language :: Python :: 3.9
Requires-Python: >=3.6
Requires-Dist: Django (>=2.2)
Requires-Dist: python3-saml (>=1.9.0)
Provides-Extra: dev
Requires-Dist: check-manifest ; extra == 'dev'
